HISTORY.rst
LICENSE
MANIFEST.in
README.rst
setup.cfg
setup.py
dadd/__init__.py
dadd.egg-info/PKG-INFO
dadd.egg-info/SOURCES.txt
dadd.egg-info/dependency_links.txt
dadd.egg-info/entry_points.txt
dadd.egg-info/not-zip-safe
dadd.egg-info/requires.txt
dadd.egg-info/top_level.txt
docs/Makefile
docs/authors.rst
docs/conf.py
docs/contributing.rst
docs/history.rst
docs/index.rst
docs/installation.rst
docs/make.bat
docs/readme.rst
docs/usage.rst
tests/__init__.py
tests/lsspec.json
tests/test_master.py
tests/test_runner.py
tests/test_worker.py