Metadata-Version: 1.1
Name: dadd
Version: 0.2.4
Summary: Dadd administers daemons.
Home-page: https://github.com/ionrock/dadd
Author: Eric Larson
Author-email: eric@ionrock.org
License: BSD
Keywords: dadd
Platform: UNKNOWN
Classifier: Development Status :: 2 - Pre-Alpha
Classifier: Intended Audience :: Developers
Classifier: License :: OSI Approved :: BSD License
Classifier: Natural Language :: English
Classifier: Programming Language :: Python :: 2
Classifier: Programming Language :: Python :: 2.6
Classifier: Programming Language :: Python :: 2.7
Classifier: Programming Language :: Python :: 3
Classifier: Programming Language :: Python :: 3.3
Classifier: Programming Language :: Python :: 3.4
